tspop.py
tspop-0.0.2.dist-info/LICENCE.txt
tspop-0.0.2.dist-info/METADATA
tspop-0.0.2.dist-info/WHEEL
tspop-0.0.2.dist-info/top_level.txt
tspop-0.0.2.dist-info/RECORD
